funnyjoke/__init__.py
funnyjoke/fastjoke.cpython-36m-x86_64-linux-gnu.so
funnyjoke-0.6.data/scripts/tell.py
funnyjoke-0.6.dist-info/METADATA
funnyjoke-0.6.dist-info/WHEEL
funnyjoke-0.6.dist-info/top_level.txt
funnyjoke-0.6.dist-info/RECORD
