Metadata-Version: 2.1
Name: funnyjoke
Version: 0.6
Summary: The funniest joke in the world
Home-page: UNKNOWN
Author: Flying Circus
Author-email: UNKNOWN
License: MIT
Platform: UNKNOWN
